MANIFEST.in
README.txt
setup.py
docs/HISTORY.txt
docs/LICENSE.txt
src/infrae/__init__.py
src/infrae.i18nextract.egg-info/PKG-INFO
src/infrae.i18nextract.egg-info/SOURCES.txt
src/infrae.i18nextract.egg-info/dependency_links.txt
src/infrae.i18nextract.egg-info/entry_points.txt
src/infrae.i18nextract.egg-info/namespace_packages.txt
src/infrae.i18nextract.egg-info/requires.txt
src/infrae.i18nextract.egg-info/top_level.txt
src/infrae/i18nextract/__init__.py
src/infrae/i18nextract/extract.py
src/infrae/i18nextract/formulator_extract.py
src/infrae/i18nextract/manage.py
src/infrae/i18nextract/metadata_extract.py
src/infrae/i18nextract/utils.py