Metadata-Version: 1.0
Name: infrae.i18nextract
Version: 1.3.1
Summary: Buildout recipe to extract i18n files in Silva
Home-page: https://svn.infrae.com/buildout/infrae.i18nextract/trunk/
Author: Sylvain Viollon
Author-email: info@infrae.com
License: ZPL 2.1
Keywords: i18n extract formulator buildout
Platform: UNKNOWN
Classifier: Framework :: Buildout
Classifier: License :: OSI Approved :: Zope Public License
Classifier: Topic :: Software Development :: Version Control
